rmq_rpc/__init__.py
rmq_rpc/client.py
rmq_rpc/constant.py
rmq_rpc/enums.py
rmq_rpc/py.typed
rmq_rpc/serializers.py
rmq_rpc/server.py
rmq_rpc-1.0.0.dist-info/WHEEL
rmq_rpc-1.0.0.dist-info/METADATA
rmq_rpc-1.0.0.dist-info/licenses/LICENSE
rmq_rpc-1.0.0.dist-info/RECORD
