Metadata-Version: 2.1
Name: rmq-rpc
Version: 1.0.0
Summary: A lightweight RPC based on RabbitMQ.
License: MIT
Author-email: aprilahijriyan <hijriyan23@gmail.com>
Requires-Python: >=3.9,<3.10
Requires-Dist: aio-pika>=8.3.0
